nt2/__init__.py
nt2/casters.py
nt2/converters.py
nt2/dumpers.py
nt2/requirements.in
nt2/requirements.txt
nt2/toml-requirements.in
nt2/toml-requirements.txt
nt2/ui.py
nt2/yamlpath_tools.py
nt2-0.2.7.dist-info/entry_points.txt
nt2-0.2.7.dist-info/LICENSE
nt2-0.2.7.dist-info/WHEEL
nt2-0.2.7.dist-info/METADATA
nt2-0.2.7.dist-info/RECORD
