Metadata-Version: 2.1
Name: nt2
Version: 0.2.7
Summary: CLI to convert between NestedText and JSON, YAML or TOML, with explicit type casting.
Keywords: NestedText,JSON,YAML,TOML
Author: Andy Kluger
Requires-Python: >=3.7
Classifier: Programming Language :: Python :: 3.7
Classifier: Programming Language :: Python :: 3.8
Classifier: Programming Language :: Python :: 3.9
Classifier: Programming Language :: Python :: 3.10
Classifier: Programming Language :: Python :: 3.11
Classifier: Programming Language :: Python :: 3.12
Classifier: Programming Language :: Python :: 3.13
Classifier: Environment :: Console
Classifier: Operating System :: MacOS
Classifier: Operating System :: Microsoft :: Windows
Classifier: Operating System :: POSIX :: Linux
Classifier: Topic :: Text Processing :: Markup
Classifier: Topic :: Utilities
Requires-Dist: cattrs
Requires-Dist: nestedtext
Requires-Dist: plumbum
Requires-Dist: rich
Requires-Dist: ruamel.yaml
Requires-Dist: yamlpath>=3.6.9
Requires-Dist: darglint ; extra == "dev"
Requires-Dist: flit ; extra == "dev"
Requires-Dist: ipython ; extra == "dev"
Requires-Dist: nestedtext ; extra == "dev"
Requires-Dist: nox ; extra == "dev"
Requires-Dist: plumbum ; extra == "dev"
Requires-Dist: pyright ; extra == "dev"
Requires-Dist: ruff ; extra == "dev"
Requires-Dist: ssort ; extra == "dev"
Requires-Dist: taskipy ; extra == "dev"
Requires-Dist: tomli ; extra == "dev"
Requires-Dist: tomli-w ; extra == "dev"
Requires-Dist: ward ; extra == "dev"
Requires-Dist: md-toc ; extra == "doc"
Requires-Dist: plumbum ; extra == "doc"
Requires-Dist: pydoctor ; extra == "doc"
Requires-Dist: wheezy.template ; extra == "doc"
Requires-Dist: darglint ; extra == "fmt"
Requires-Dist: ruff ; extra == "fmt"
Requires-Dist: ssort ; extra == "fmt"
Requires-Dist: nestedtext ; extra == "test"
Requires-Dist: plumbum ; extra == "test"
Requires-Dist: tomli ; extra == "test"
Requires-Dist: tomli-w ; extra == "test"
Requires-Dist: ward ; extra == "test"
Requires-Dist: nestedtext ; extra == "test-without-toml"
Requires-Dist: plumbum ; extra == "test-without-toml"
Requires-Dist: ward ; extra == "test-without-toml"
Requires-Dist: tomli ; extra == "toml"
Requires-Dist: tomli-w ; extra == "toml"
Project-URL: Home, https://github.com/andydecleyre/nestedtextto
Provides-Extra: dev
Provides-Extra: doc
Provides-Extra: fmt
Provides-Extra: test
Provides-Extra: test-without-toml
Provides-Extra: toml
